lib4package/__init__.py
lib4package/metadata.py
lib4package/version.py
lib4package-0.3.3.dist-info/LICENSE
lib4package-0.3.3.dist-info/METADATA
lib4package-0.3.3.dist-info/WHEEL
lib4package-0.3.3.dist-info/top_level.txt
lib4package-0.3.3.dist-info/RECORD
